stm32loader/.gitignore
stm32loader/__init__.py
stm32loader/__main__.py
stm32loader/args.py
stm32loader/bootloader.py
stm32loader/devices.py
stm32loader/hexfile.py
stm32loader/main.py
stm32loader/uart.py
stm32loader-0.7.1.dist-info/entry_points.txt
stm32loader-0.7.1.dist-info/LICENSE
stm32loader-0.7.1.dist-info/WHEEL
stm32loader-0.7.1.dist-info/METADATA
stm32loader-0.7.1.dist-info/RECORD
