Metadata-Version: 2.1
Name: stm32loader
Version: 0.7.1
Summary: Flash firmware to STM32 microcontrollers using Python.
Author: jsnyder
Author-email: Floris Lambrechts <florisla@gmail.com>
Requires-Python: >=3.9
Classifier: License :: OSI Approved :: GNU General Public License v3 or later (GPLv3+)
Classifier: Programming Language :: Python
Classifier: Programming Language :: Python :: 3
Classifier: Programming Language :: Python :: 3.9
Classifier: Programming Language :: Python :: 3.10
Classifier: Programming Language :: Python :: 3.11
Classifier: Programming Language :: Python :: Implementation :: CPython
Classifier: Programming Language :: Python :: Implementation :: PyPy
Classifier: Natural Language :: English
Classifier: Operating System :: OS Independent
Requires-Dist: pyserial
Requires-Dist: progress
Requires-Dist: wheel ; extra == "dev"
Requires-Dist: twine ; extra == "dev"
Requires-Dist: pylint ; extra == "dev"
Requires-Dist: flake8 ; extra == "dev"
Requires-Dist: flake8-isort ; extra == "dev"
Requires-Dist: black ; extra == "dev"
Requires-Dist: bump-my-version ; extra == "dev"
Requires-Dist: nox ; extra == "dev"
Requires-Dist: cogapp ; extra == "dev"
Requires-Dist: intelhex ; extra == "hex"
Project-URL: BugTracker, https://github.com/florisla/stm32loader/issues
Project-URL: Home, https://github.com/florisla/stm32loader
Project-URL: SourceCode, https://github.com/florisla/stm32loader
Provides-Extra: dev
Provides-Extra: hex
